odoo10_addon_sale_mrp_link-10.0.1.0.1-py3.8-nspkg.pth
odoo/addons/sale_mrp_link/README.rst
odoo/addons/sale_mrp_link/__init__.py
odoo/addons/sale_mrp_link/__manifest__.py
odoo/addons/sale_mrp_link/i18n/ca.po
odoo/addons/sale_mrp_link/i18n/es.po
odoo/addons/sale_mrp_link/i18n/it.po
odoo/addons/sale_mrp_link/i18n/sale_mrp_link.pot
odoo/addons/sale_mrp_link/models/__init__.py
odoo/addons/sale_mrp_link/models/mrp_production.py
odoo/addons/sale_mrp_link/models/procurement_order.py
odoo/addons/sale_mrp_link/models/sale_order.py
odoo/addons/sale_mrp_link/readme/CONTRIBUTORS.rst
odoo/addons/sale_mrp_link/readme/DESCRIPTION.rst
odoo/addons/sale_mrp_link/readme/ROADMAP.rst
odoo/addons/sale_mrp_link/static/description/icon.png
odoo/addons/sale_mrp_link/static/description/index.html
odoo/addons/sale_mrp_link/tests/__init__.py
odoo/addons/sale_mrp_link/tests/test_mrp_sale_link.py
odoo/addons/sale_mrp_link/views/mrp_production.xml
odoo/addons/sale_mrp_link/views/sale_order.xml
odoo10_addon_sale_mrp_link-10.0.1.0.1.dist-info/METADATA
odoo10_addon_sale_mrp_link-10.0.1.0.1.dist-info/WHEEL
odoo10_addon_sale_mrp_link-10.0.1.0.1.dist-info/namespace_packages.txt
odoo10_addon_sale_mrp_link-10.0.1.0.1.dist-info/top_level.txt
odoo10_addon_sale_mrp_link-10.0.1.0.1.dist-info/RECORD
