Metadata-Version: 2.1
Name: odoo10-addon-sale-mrp-link
Version: 10.0.1.0.1
Summary: Show manufacturing orders generated from sales order
Home-page: https://github.com/OCA/sale-workflow
Author: Akretion, Agile Business Group, Odoo Community Association (OCA)
Author-email: support@odoo-community.org
License: AGPL-3
Platform: UNKNOWN
Classifier: Programming Language :: Python
Classifier: Framework :: Odoo
Classifier: Framework :: Odoo :: 10.0
Classifier: License :: OSI Approved :: GNU Affero General Public License v3
Classifier: Development Status :: 5 - Production/Stable
Requires-Python: ~=2.7
Requires-Dist: odoo (<10.1dev,>=10.0)
